json_stream_to_standard_types.py
json_stream_to_standard_types-0.1.0.dist-info/WHEEL
json_stream_to_standard_types-0.1.0.dist-info/METADATA
json_stream_to_standard_types-0.1.0.dist-info/RECORD
