Metadata-Version: 2.1
Name: json-stream-to-standard-types
Version: 0.1.0
Summary: Convert json-stream objects to standard Python dicts and lists
Author: smheidrich
Author-email: smheidrich@weltenfunktion.de
Requires-Python: >=3.7,<4.0
Classifier: Programming Language :: Python :: 3
Classifier: Programming Language :: Python :: 3.10
Classifier: Programming Language :: Python :: 3.7
Classifier: Programming Language :: Python :: 3.8
Classifier: Programming Language :: Python :: 3.9
Requires-Dist: json-stream (>=1,<3)
